lakedrive/__init__.py
lakedrive/__main__.py
lakedrive/cli.py
lakedrive/common/__init__.py
lakedrive/common/config.py
lakedrive/config.py
lakedrive/core/__init__.py
lakedrive/core/executors.py
lakedrive/core/handlers.py
lakedrive/core/helpers.py
lakedrive/core/list_filter.py
lakedrive/core/objects.py
lakedrive/core/sync.py
lakedrive/httplibs/__init__.py
lakedrive/httplibs/connection.py
lakedrive/httplibs/helpers.py
lakedrive/httplibs/objects.py
lakedrive/httplibs/request.py
lakedrive/localfs/files.py
lakedrive/localfs/handler.py
lakedrive/py.typed
lakedrive/s3/__init__.py
lakedrive/s3/bucket.py
lakedrive/s3/files.py
lakedrive/s3/handler.py
lakedrive/s3/headers.py
lakedrive/s3/objects.py
lakedrive/s3/testfiles/1.txt
lakedrive/s3/testfiles/2.txt
lakedrive/s3/testfiles/3.txt
lakedrive/s3/xmlparse.py
lakedrive-0.1.0.dist-info/WHEEL
lakedrive-0.1.0.dist-info/METADATA
lakedrive-0.1.0.dist-info/RECORD
