Metadata-Version: 2.1
Name: lakedrive
Version: 0.1.0
Summary: 
Author: anthony
Author-email: anthony.potappel@gmail.com
Requires-Python: >=3.7,<4.0
Classifier: Programming Language :: Python :: 3
Classifier: Programming Language :: Python :: 3.10
Classifier: Programming Language :: Python :: 3.7
Classifier: Programming Language :: Python :: 3.8
Classifier: Programming Language :: Python :: 3.9
Requires-Dist: coverage (>=6.2,<7.0)
